{
  "$schema": "https://schema.management.azure.com/schemas/2015-01-01/deploymentTemplate.json",
  "contentVersion": "1.0.0.0",
  "parameters": {
     "FGProtectedAddress":{
         "type": "string",
         "defaultValue": "",
         "metadata": {
             "description":"static ip address"
         }
     },
     "subnet2Ref":{
        "type": "string",
         "defaultValue": "",
         "metadata": {
             "description":"subnet2 Ref"
         }
     }
  },
   "variables":{
  },
   "resources": [
         {
            "apiVersion": "2015-01-01",
            "type": "Microsoft.Resources/deployments",
            "name": "SettingUpnetworkInterface",
            "dependsOn": [
                "[concat('Microsoft.Resources/deployments/', 'SettingUpVirtualNetwork')]"
            ],
            "properties": {
                "ipConfigurations": [
                    {
                        "name": "ipconfig1",
                        "properties": {
                            "privateIPAllocationMethod": "Static",
                            "privateIPAddress": "[parameters('FGProtectedAddress')]",
                            "subnet": {
                                "id": "[parameters('subnet2Ref')]"
                            }
                        }
                    }
                ],
                "enableIPForwarding": true
            }
        }
   ]
}
